quant_pml/__init__.py
quant_pml/feature_processor.py
quant_pml/py.typed
quant_pml/runner.py
quant_pml/ap/__init__.py
quant_pml/ap/base_asset_pricer.py
quant_pml/ap/ipca_factor_model.py
quant_pml/ap/kns_factor_model.py
quant_pml/ap/uncond_factor_model.py
quant_pml/backtest/__init__.py
quant_pml/backtest/assessor.py
quant_pml/backtest/backtester.py
quant_pml/backtest/plot.py
quant_pml/backtest/research_us_backtest.py
quant_pml/backtest/russell3000_backtest.py
quant_pml/backtest/transaction_costs_charger.py
quant_pml/base/__init__.py
quant_pml/base/currencies.py
quant_pml/base/prices.py
quant_pml/base/returns.py
quant_pml/config/__init__.py
quant_pml/config/base_experiment_config.py
quant_pml/config/base_experiment_config_v2.py
quant_pml/config/experiment_config.py
quant_pml/config/jkp_experiment_config.py
quant_pml/config/research_us_experiment_config.py
quant_pml/config/research_us_trading_config.py
quant_pml/config/russell_3000_experiment_config.py
quant_pml/config/russia_experiment_config.py
quant_pml/config/spx_experiment_config.py
quant_pml/config/topn_experiment_config.py
quant_pml/config/trading_config.py
quant_pml/config/us_experiment_config.py
quant_pml/data_handlers/__init__.py
quant_pml/data_handlers/additional_data.py
quant_pml/data_handlers/create_compustat_dataset.py
quant_pml/data_handlers/create_crsp_dataset.py
quant_pml/data_handlers/create_spx_dataset.py
quant_pml/data_handlers/dataset.py
quant_pml/data_handlers/dataset_builder_functions.py
quant_pml/data_handlers/prepare_data.py
quant_pml/data_handlers/universe_builder_functions.py
quant_pml/dataset/__init__.py
quant_pml/dataset/dataset_builder.py
quant_pml/dataset/dnk_features_targets.py
quant_pml/date/__init__.py
quant_pml/date/pd_date.py
quant_pml/estimation/__init__.py
quant_pml/estimation/base_estimator.py
quant_pml/estimation/covariance/__init__.py
quant_pml/estimation/covariance/base_cov_estimator.py
quant_pml/estimation/covariance/sample_cov_estimator.py
quant_pml-0.1.0.dist-info/licenses/LICENSE
quant_pml-0.1.0.dist-info/METADATA
quant_pml-0.1.0.dist-info/WHEEL
quant_pml-0.1.0.dist-info/top_level.txt
quant_pml-0.1.0.dist-info/RECORD
