Metadata-Version: 2.4
Name: quant-pml
Version: 0.1.0
Author: Viacheslav Buchkov
License-Expression: MIT
Keywords: quant,quantitative finance,machine learning
Requires-Python: ==3.12.5
License-File: LICENSE
Requires-Dist: statsmodels>=0.14.4
Requires-Dist: scikit-learn>=1.5.2
Requires-Dist: numpy>=2.2.4
Requires-Dist: pandas>=2.3.1
Requires-Dist: matplotlib>=3.10.1
Requires-Dist: qpsolvers>=4.5.0
Requires-Dist: torch==2.8.0
Requires-Dist: pyarrow==20.0.0
Requires-Dist: fastparquet==2024.11.0
Requires-Dist: tqdm>=4.67.1
Requires-Dist: scipy>=1.16.1
Requires-Dist: optuna==4.4.0
Requires-Dist: plotly>=6.2.0
Requires-Dist: openpyxl>=3.1.5
Requires-Dist: polars==1.34.0
Dynamic: license-file
